Metadata-Version: 2.1
Name: fetchfox
Version: 1.0.1
Summary: Fetchfox automates installation of Firefox on Linux systems
Home-page: https://github.com/Addvilz/fetchfox
Author: Addvilz
Author-email: mrtreinis@gmail.com
License: Apache 2.0
Download-URL: https://github.com/Addvilz/fetchfox
Platform: UNIX
Classifier: Development Status :: 5 - Production/Stable
Classifier: Environment :: Console
Classifier: Intended Audience :: System Administrators
Classifier: License :: OSI Approved :: Apache Software License
Classifier: Operating System :: POSIX :: Linux
Classifier: Operating System :: POSIX
Classifier: Operating System :: Unix
Classifier: Programming Language :: Python :: 3 :: Only
